tom_alerts_dash/__init__.py
tom_alerts_dash/admin.py
tom_alerts_dash/alerts.py
tom_alerts_dash/apps.py
tom_alerts_dash/dash.py
tom_alerts_dash/urls.py
tom_alerts_dash/views.py
tom_alerts_dash/brokers/__init__.py
tom_alerts_dash/brokers/alerce.py
tom_alerts_dash/brokers/mars.py
tom_alerts_dash/brokers/scimma.py
tom_alerts_dash/dash_apps/__init__.py
tom_alerts_dash/dash_apps/query_list_app.py
tom_alerts_dash/migrations/__init__.py
tom_alerts_dash/templates/tom_alerts_dash/brokerquery_browse.html
tom_alerts_dash/templates/tom_alerts_dash/brokerquery_list.html
tom_alerts_dash/tests/__init__.py
tom_alerts_dash/tests/factories.py
tom_alerts_dash/tests/tests.py
tom_alerts_dash/tests/brokers/__init__.py
tom_alerts_dash/tests/brokers/test_alerce.py
tom_alerts_dash/tests/brokers/test_mars.py
tom_alerts_dash/tests/brokers/test_scimma.py
tom_alerts_dash_base/__init__.py
tom_alerts_dash_base/asgi.py
tom_alerts_dash_base/settings.py
tom_alerts_dash_base/urls.py
tom_alerts_dash_base/wsgi.py
tom_alerts_dash-0.1.2.dist-info/LICENSE
tom_alerts_dash-0.1.2.dist-info/METADATA
tom_alerts_dash-0.1.2.dist-info/WHEEL
tom_alerts_dash-0.1.2.dist-info/top_level.txt
tom_alerts_dash-0.1.2.dist-info/RECORD
