Metadata-Version: 2.1
Name: tom-alerts-dash
Version: 0.1.2
Summary: Plotly Dash-based broker app for the TOM Toolkit
Home-page: https://tom-toolkit.readthedocs.io
Author: TOM Toolkit Project
Author-email: dcollom@lco.global
License: UNKNOWN
Keywords: tomtoolkit,astronomy,astrophysics,cosmology,science,fits,observatory
Platform: UNKNOWN
Classifier: Development Status :: 3 - Alpha
Classifier: Intended Audience :: Science/Research
Classifier: License :: OSI Approved :: BSD License
Classifier: Operating System :: OS Independent
Classifier: Programming Language :: Python :: 3
Classifier: Programming Language :: Python :: 3.7
Classifier: Topic :: Scientific/Engineering :: Astronomy
Classifier: Topic :: Scientific/Engineering :: Physics
Requires-Dist: tomtoolkit (>=2.6.3)
Requires-Dist: django-plotly-dash (==1.4.2)
Requires-Dist: dash-bootstrap-components (==0.10.3)
Requires-Dist: whitenoise (==5.2.0)
Requires-Dist: dpd-static-support
Requires-Dist: django-bootstrap4
Provides-Extra: scimma
Requires-Dist: tom-scimma (>=1.1.0) ; extra == 'scimma'
Provides-Extra: test
Requires-Dist: tom-scimma ; extra == 'test'
Requires-Dist: factory-boy ; extra == 'test'
